django_badges-1.0.0.dist-info/RECORD
django_badges-1.0.0.dist-info/metadata.json
django_badges-1.0.0.dist-info/WHEEL
django_badges-1.0.0.dist-info/DESCRIPTION.rst
django_badges-1.0.0.dist-info/top_level.txt
django_badges-1.0.0.dist-info/METADATA
badges/signals.py
badges/listeners.py
badges/models.py
badges/__init__.py
badges/admin.py
badges/utils.py
badges/urls.py
badges/views.py
badges/managers.py
badges/templatetags/badges_tags.py
badges/templatetags/__init__.py
badges/migrations/__init__.py
badges/migrations/0002_auto_20150513_0429.py
badges/migrations/0001_initial.py
